py2jnb/__init__.py
py2jnb/__main__.py
py2jnb/converter.py
py2jnb/reader.py
py2jnb/tools.py
tests/__init__.py
tests/test_conversion.py
py2jnb-0.0.5.dist-info/LICENSE
py2jnb-0.0.5.dist-info/METADATA
py2jnb-0.0.5.dist-info/WHEEL
py2jnb-0.0.5.dist-info/top_level.txt
py2jnb-0.0.5.dist-info/RECORD
