Metadata-Version: 2.1
Name: py2jnb
Version: 0.0.5
Summary: Utility to turn IPython scripts into Jupyter Notebook format. Forked from py2nb project.
Home-page: https://github.com/MarcusJones/py2jnb
Author: M.Jones, forked from Siu Kwan Lam
Author-email: jones.0bj3@gmail.com
License: Apache Software License 2.0
Platform: UNKNOWN
Classifier: Development Status :: 2 - Pre-Alpha
Classifier: Intended Audience :: Developers
Classifier: License :: OSI Approved :: Apache Software License
Classifier: Natural Language :: English
Classifier: Programming Language :: Python :: 3
Requires-Dist: nbformat
Requires-Dist: IPython
